{
    "name": "buzzwole",
    "id": 794,
    "info": {
        "species": "swollen pok\u00e9mon",
        "abilities": [
            {
                "name": "beast-boost",
                "is_hidden": false
            }
        ],
        "types": [
            "bug",
            "fighting"
        ],
        "height": 2.4,
        "weight": 333.6
    },
    "sprites": {
        "home": "images/pokemon/buzzwole.png",
        "artwork": "https://raw.githubusercontent.com/PokeAPI/sprites/master/sprites/pokemon/other/official-artwork/794.png"
    },
    "moves": "data/moves/buzzwole.json",
    "location": "data/location/buzzwole.json",
    "base_stats": {
        "hp": 107,
        "attack": 139,
        "defense": 139,
        "sp. atk": 53,
        "sp. def": 53,
        "speed": 79
    },
    "entry": "buzzwole goes around showing off its abnormally swollen muscles. it is one kind of ultra beast.",
    "training": {
        "base_exp": 257,
        "capture_rate": 45,
        "growth_rate": "slow"
    },
    "breeding": {
        "base_happiness": 0,
        "egg_group": [
            "no-eggs"
        ],
        "gender": {
            "male": 0,
            "female": 0
        },
        "egg_cycle": {
            "hatch_counter": 120,
            "steps": 30855
        }
    }
}