{
    "name": "calyrex",
    "id": 898,
    "info": {
        "species": "king pok\u00e9mon",
        "abilities": [
            {
                "name": "unnerve",
                "is_hidden": false
            }
        ],
        "types": [
            "psychic",
            "grass"
        ],
        "height": 1.1,
        "weight": 7.7
    },
    "sprites": {
        "home": "images/pokemon/calyrex.png",
        "artwork": "https://raw.githubusercontent.com/PokeAPI/sprites/master/sprites/pokemon/other/official-artwork/898.png"
    },
    "moves": "data/moves/calyrex.json",
    "location": "data/location/calyrex.json",
    "base_stats": {
        "hp": 100,
        "attack": 80,
        "defense": 80,
        "sp. atk": 80,
        "sp. def": 80,
        "speed": 80
    },
    "entry": "calyrex is known in legend as a king that ruled over galar in ancient times. it has the power to cause hearts to mend and plants to spring forth.",
    "training": {
        "base_exp": 250,
        "capture_rate": 3,
        "growth_rate": "slow"
    },
    "breeding": {
        "base_happiness": 100,
        "egg_group": [],
        "gender": {
            "male": 0,
            "female": 0
        },
        "egg_cycle": {
            "hatch_counter": 120,
            "steps": 30855
        }
    }
}