{
    "location": [
        {
            "game": [
                "diamond",
                "pearl",
                "platinum"
            ],
            "area": [
                "sinnoh-route-224-area"
            ]
        },
        {
            "game": [
                "gold",
                "silver",
                "crystal",
                "heartgold",
                "soulsilver"
            ],
            "area": [
                "ruins-of-alph-outside"
            ]
        },
        {
            "game": [
                "ruby",
                "sapphire",
                "emerald"
            ],
            "area": [
                "hoenn-safari-zone-neacro-bike-area",
                "hoenn-safari-zone-sw",
                "hoenn-safari-zone-se"
            ]
        },
        {
            "game": [
                "firered",
                "leafgreen"
            ],
            "area": [
                "ruin-valley-area"
            ]
        }
    ]
}