{
    "moves": [
        {
            "name": "fire-punch",
            "method": "level-up",
            "level": 1
        },
        {
            "name": "ice-punch",
            "method": "level-up",
            "level": 1
        },
        {
            "name": "thunder-punch",
            "method": "level-up",
            "level": 1
        },
        {
            "name": "jump-kick",
            "method": "level-up",
            "level": 35
        },
        {
            "name": "rolling-kick",
            "method": "level-up",
            "level": 15
        },
        {
            "name": "counter",
            "method": "level-up",
            "level": 1
        },
        {
            "name": "toxic",
            "method": "machine",
            "level": 0
        },
        {
            "name": "double-team",
            "method": "machine",
            "level": 0
        },
        {
            "name": "rest",
            "method": "machine",
            "level": 0
        },
        {
            "name": "rock-slide",
            "method": "machine",
            "level": 0
        },
        {
            "name": "substitute",
            "method": "machine",
            "level": 0
        },
        {
            "name": "thief",
            "method": "machine",
            "level": 0
        },
        {
            "name": "protect",
            "method": "machine",
            "level": 0
        },
        {
            "name": "false-swipe",
            "method": "machine",
            "level": 0
        },
        {
            "name": "swagger",
            "method": "machine",
            "level": 0
        },
        {
            "name": "sleep-talk",
            "method": "machine",
            "level": 0
        },
        {
            "name": "return",
            "method": "machine",
            "level": 0
        },
        {
            "name": "frustration",
            "method": "machine",
            "level": 0
        },
        {
            "name": "pursuit",
            "method": "level-up",
            "level": 1
        },
        {
            "name": "hidden-power",
            "method": "machine",
            "level": 0
        },
        {
            "name": "psych-up",
            "method": "machine",
            "level": 0
        },
        {
            "name": "shadow-ball",
            "method": "machine",
            "level": 0
        },
        {
            "name": "will-o-wisp",
            "method": "machine",
            "level": 0
        },
        {
            "name": "facade",
            "method": "machine",
            "level": 0
        },
        {
            "name": "role-play",
            "method": "level-up",
            "level": 30
        },
        {
            "name": "brick-break",
            "method": "machine",
            "level": 0
        },
        {
            "name": "endeavor",
            "method": "level-up",
            "level": 60
        },
        {
            "name": "rock-tomb",
            "method": "machine",
            "level": 0
        },
        {
            "name": "shadow-punch",
            "method": "level-up",
            "level": 26
        },
        {
            "name": "bulk-up",
            "method": "machine",
            "level": 0
        },
        {
            "name": "calm-mind",
            "method": "machine",
            "level": 0
        },
        {
            "name": "feint",
            "method": "level-up",
            "level": 11
        },
        {
            "name": "close-combat",
            "method": "level-up",
            "level": 50
        },
        {
            "name": "payback",
            "method": "machine",
            "level": 0
        },
        {
            "name": "assurance",
            "method": "level-up",
            "level": 1
        },
        {
            "name": "fling",
            "method": "machine",
            "level": 0
        },
        {
            "name": "copycat",
            "method": "level-up",
            "level": 20
        },
        {
            "name": "sucker-punch",
            "method": "level-up",
            "level": 56
        },
        {
            "name": "force-palm",
            "method": "level-up",
            "level": 5
        },
        {
            "name": "poison-jab",
            "method": "machine",
            "level": 0
        },
        {
            "name": "drain-punch",
            "method": "level-up",
            "level": 1
        },
        {
            "name": "focus-blast",
            "method": "machine",
            "level": 0
        },
        {
            "name": "giga-impact",
            "method": "machine",
            "level": 0
        },
        {
            "name": "shadow-claw",
            "method": "machine",
            "level": 0
        },
        {
            "name": "shadow-sneak",
            "method": "level-up",
            "level": 1
        },
        {
            "name": "stone-edge",
            "method": "machine",
            "level": 0
        },
        {
            "name": "grass-knot",
            "method": "machine",
            "level": 0
        },
        {
            "name": "smack-down",
            "method": "machine",
            "level": 0
        },
        {
            "name": "low-sweep",
            "method": "machine",
            "level": 0
        },
        {
            "name": "round",
            "method": "machine",
            "level": 0
        },
        {
            "name": "echoed-voice",
            "method": "machine",
            "level": 0
        },
        {
            "name": "acrobatics",
            "method": "machine",
            "level": 0
        },
        {
            "name": "work-up",
            "method": "machine",
            "level": 0
        },
        {
            "name": "confide",
            "method": "machine",
            "level": 0
        },
        {
            "name": "laser-focus",
            "method": "level-up",
            "level": 1
        },
        {
            "name": "spectral-thief",
            "method": "level-up",
            "level": 45
        }
    ]
}