{
    "moves": [
        {
            "name": "tackle",
            "method": "level-up",
            "level": 1
        },
        {
            "name": "take-down",
            "method": "egg",
            "level": 0
        },
        {
            "name": "double-edge",
            "method": "tutor",
            "level": 0
        },
        {
            "name": "twineedle",
            "method": "egg",
            "level": 0
        },
        {
            "name": "leer",
            "method": "level-up",
            "level": 20
        },
        {
            "name": "supersonic",
            "method": "level-up",
            "level": 8
        },
        {
            "name": "water-gun",
            "method": "level-up",
            "level": 1
        },
        {
            "name": "hydro-pump",
            "method": "level-up",
            "level": 61
        },
        {
            "name": "surf",
            "method": "machine",
            "level": 0
        },
        {
            "name": "ice-beam",
            "method": "machine",
            "level": 0
        },
        {
            "name": "blizzard",
            "method": "machine",
            "level": 0
        },
        {
            "name": "bubble-beam",
            "method": "egg",
            "level": 0
        },
        {
            "name": "aurora-beam",
            "method": "level-up",
            "level": 37
        },
        {
            "name": "toxic",
            "method": "machine",
            "level": 0
        },
        {
            "name": "rage",
            "method": "machine",
            "level": 0
        },
        {
            "name": "teleport",
            "method": "machine",
            "level": 0
        },
        {
            "name": "mimic",
            "method": "tutor",
            "level": 0
        },
        {
            "name": "screech",
            "method": "egg",
            "level": 0
        },
        {
            "name": "double-team",
            "method": "machine",
            "level": 0
        },
        {
            "name": "withdraw",
            "method": "level-up",
            "level": 4
        },
        {
            "name": "barrier",
            "method": "egg",
            "level": 0
        },
        {
            "name": "reflect",
            "method": "machine",
            "level": 0
        },
        {
            "name": "bide",
            "method": "machine",
            "level": 0
        },
        {
            "name": "self-destruct",
            "method": "tutor",
            "level": 0
        },
        {
            "name": "clamp",
            "method": "level-up",
            "level": 25
        },
        {
            "name": "swift",
            "method": "tutor",
            "level": 0
        },
        {
            "name": "explosion",
            "method": "machine",
            "level": 0
        },
        {
            "name": "rest",
            "method": "machine",
            "level": 0
        },
        {
            "name": "tri-attack",
            "method": "machine",
            "level": 0
        },
        {
            "name": "substitute",
            "method": "machine",
            "level": 0
        },
        {
            "name": "snore",
            "method": "tutor",
            "level": 0
        },
        {
            "name": "curse",
            "method": "machine",
            "level": 0
        },
        {
            "name": "protect",
            "method": "machine",
            "level": 0
        },
        {
            "name": "icy-wind",
            "method": "tutor",
            "level": 0
        },
        {
            "name": "endure",
            "method": "machine",
            "level": 0
        },
        {
            "name": "swagger",
            "method": "machine",
            "level": 0
        },
        {
            "name": "attract",
            "method": "machine",
            "level": 0
        },
        {
            "name": "sleep-talk",
            "method": "machine",
            "level": 0
        },
        {
            "name": "return",
            "method": "machine",
            "level": 0
        },
        {
            "name": "frustration",
            "method": "machine",
            "level": 0
        },
        {
            "name": "rapid-spin",
            "method": "egg",
            "level": 0
        },
        {
            "name": "hidden-power",
            "method": "machine",
            "level": 0
        },
        {
            "name": "rain-dance",
            "method": "machine",
            "level": 0
        },
        {
            "name": "whirlpool",
            "method": "level-up",
            "level": 40
        },
        {
            "name": "hail",
            "method": "machine",
            "level": 0
        },
        {
            "name": "facade",
            "method": "machine",
            "level": 0
        },
        {
            "name": "secret-power",
            "method": "machine",
            "level": 0
        },
        {
            "name": "dive",
            "method": "machine",
            "level": 0
        },
        {
            "name": "icicle-spear",
            "method": "egg",
            "level": 0
        },
        {
            "name": "iron-defense",
            "method": "level-up",
            "level": 49
        },
        {
            "name": "mud-shot",
            "method": "egg",
            "level": 0
        },
        {
            "name": "rock-blast",
            "method": "egg",
            "level": 0
        },
        {
            "name": "water-pulse",
            "method": "egg",
            "level": 0
        },
        {
            "name": "brine",
            "method": "level-up",
            "level": 44
        },
        {
            "name": "natural-gift",
            "method": "machine",
            "level": 0
        },
        {
            "name": "payback",
            "method": "machine",
            "level": 0
        },
        {
            "name": "aqua-ring",
            "method": "egg",
            "level": 0
        },
        {
            "name": "avalanche",
            "method": "egg",
            "level": 0
        },
        {
            "name": "ice-shard",
            "method": "level-up",
            "level": 28
        },
        {
            "name": "captivate",
            "method": "machine",
            "level": 0
        },
        {
            "name": "round",
            "method": "machine",
            "level": 0
        },
        {
            "name": "shell-smash",
            "method": "level-up",
            "level": 56
        },
        {
            "name": "razor-shell",
            "method": "level-up",
            "level": 32
        },
        {
            "name": "confide",
            "method": "machine",
            "level": 0
        }
    ]
}